dsi_bitstream-0.1.0.dist-info/METADATA
dsi_bitstream-0.1.0.dist-info/WHEEL
dsi_bitstream-0.1.0.dist-info/license_files/LICENSE-Apache-2.0
dsi_bitstream-0.1.0.dist-info/license_files/LICENSE-LGPL-2.1-or-later
dsi_bitstream/__init__.py
dsi_bitstream/dsi_bitstream.pyd
dsi_bitstream-0.1.0.dist-info/RECORD
