Metadata-Version: 2.3
Name: dsi_bitstream
Version: 0.1.0
Classifier: Programming Language :: Rust
Classifier: Programming Language :: Python :: Implementation :: CPython
Classifier: Programming Language :: Python :: Implementation :: PyPy
License-File: LICENSE-Apache-2.0
License-File: LICENSE-LGPL-2.1-or-later
Summary: Python bindings for the Rust implementation of read/write bit streams supporting several types of instantaneous codes
Keywords: bitstream,codes,compression
Author: Tommaso Fontana, Sebastiano Vigna
Author-email: tommaso.fontana.96@gmail.com, sebastiano.vigna@unimi.it
Maintainer-email: Tommaso Fontana <tommaso.fontana.96@gmail.com>
License: Apache-2.0 OR LGPL-2.1-or-later
Requires-Python: >=3.7
Project-URL: repository, http://github.com/zommiommy/dsi-bitstream-py
Project-URL: changelog, http://github.com/zommiommy/dsi-bitstream-py/blob/master/CHANGELOG.md
